[{"image": "Snap-1274.czi.jpg", "annotations": [{"label": "embryo", "coordinates": {"x": 566.5161290322582, "y": 522.3440860215054, "width": 506.0, "height": 674.0}}, {"label": "eye", "coordinates": {"x": 347.0, "y": 779.5, "width": 66.0, "height": 59.0}}, {"label": "eye", "coordinates": {"x": 400.0, "y": 831.5, "width": 68.0, "height": 51.0}}, {"label": "yolksac", "coordinates": {"x": 481.5, "y": 684.0, "width": 143.0, "height": 152.0}}, {"label": "debris", "coordinates": {"x": 985.1164383561645, "y": 370.3767123287671, "width": 231.0000000000001, "height": 323.0}}]}]