<annotation>
	<folder>5_AB 5 Gy 4 nap</folder>
	<filename>Snap-1251.czi.jpg</filename>
	<path>C:\Users\aron.gimesi\Documents\.codes\zebrafisher\labeled\5_AB 5 Gy 4 nap\Snap-1251.czi.jpg</path>
	<source>
		<database>Unknown</database>
	</source>
	<size>
		<width>1388</width>
		<height>1040</height>
		<depth>1</depth>
	</size>
	<segmented>0</segmented>
	<object>
		<name>embryo</name>
		<pose>Unspecified</pose>
		<truncated>0</truncated>
		<difficult>0</difficult>
		<bndbox>
			<xmin>529</xmin>
			<ymin>173</ymin>
			<xmax>1226</xmax>
			<ymax>719</ymax>
		</bndbox>
	</object>
	<object>
		<name>yolksac</name>
		<pose>Unspecified</pose>
		<truncated>0</truncated>
		<difficult>0</difficult>
		<bndbox>
			<xmin>992</xmin>
			<ymin>498</ymin>
			<xmax>1135</xmax>
			<ymax>622</ymax>
		</bndbox>
	</object>
	<object>
		<name>eye</name>
		<pose>Unspecified</pose>
		<truncated>0</truncated>
		<difficult>0</difficult>
		<bndbox>
			<xmin>1176</xmin>
			<ymin>601</ymin>
			<xmax>1224</xmax>
			<ymax>664</ymax>
		</bndbox>
	</object>
	<object>
		<name>eye</name>
		<pose>Unspecified</pose>
		<truncated>0</truncated>
		<difficult>0</difficult>
		<bndbox>
			<xmin>1118</xmin>
			<ymin>663</ymin>
			<xmax>1185</xmax>
			<ymax>716</ymax>
		</bndbox>
	</object>
	<object>
		<name>debris</name>
		<pose>Unspecified</pose>
		<truncated>1</truncated>
		<difficult>0</difficult>
		<bndbox>
			<xmin>893</xmin>
			<ymin>949</ymin>
			<xmax>1023</xmax>
			<ymax>1040</ymax>
		</bndbox>
	</object>
	<object>
		<name>debris</name>
		<pose>Unspecified</pose>
		<truncated>0</truncated>
		<difficult>0</difficult>
		<bndbox>
			<xmin>1016</xmin>
			<ymin>399</ymin>
			<xmax>1165</xmax>
			<ymax>557</ymax>
		</bndbox>
	</object>
	<object>
		<name>debris</name>
		<pose>Unspecified</pose>
		<truncated>0</truncated>
		<difficult>0</difficult>
		<bndbox>
			<xmin>612</xmin>
			<ymin>32</ymin>
			<xmax>801</xmax>
			<ymax>162</ymax>
		</bndbox>
	</object>
</annotation>
