<annotation>
	<folder>3_AB 15 Gy 3 nap</folder>
	<filename>Snap-924.czi.jpg</filename>
	<path>C:\Users\aron.gimesi\Documents\.codes\zebrafisher\labeled\3_AB 15 Gy 3 nap\Snap-924.czi.jpg</path>
	<source>
		<database>Unknown</database>
	</source>
	<size>
		<width>1388</width>
		<height>1040</height>
		<depth>1</depth>
	</size>
	<segmented>0</segmented>
	<object>
		<name>embryo</name>
		<pose>Unspecified</pose>
		<truncated>0</truncated>
		<difficult>0</difficult>
		<bndbox>
			<xmin>487</xmin>
			<ymin>448</ymin>
			<xmax>1141</xmax>
			<ymax>691</ymax>
		</bndbox>
	</object>
	<object>
		<name>yolksac</name>
		<pose>Unspecified</pose>
		<truncated>0</truncated>
		<difficult>0</difficult>
		<bndbox>
			<xmin>940</xmin>
			<ymin>466</ymin>
			<xmax>1062</xmax>
			<ymax>604</ymax>
		</bndbox>
	</object>
	<object>
		<name>eye</name>
		<pose>Unspecified</pose>
		<truncated>0</truncated>
		<difficult>0</difficult>
		<bndbox>
			<xmin>1070</xmin>
			<ymin>450</ymin>
			<xmax>1118</xmax>
			<ymax>490</ymax>
		</bndbox>
	</object>
	<object>
		<name>eye</name>
		<pose>Unspecified</pose>
		<truncated>0</truncated>
		<difficult>0</difficult>
		<bndbox>
			<xmin>1095</xmin>
			<ymin>515</ymin>
			<xmax>1137</xmax>
			<ymax>557</ymax>
		</bndbox>
	</object>
</annotation>
